pscdk/__init__.py
pscdk/__main__.py
pscdk/wasm_checker.py
pscdk/codon/bin/codon
pscdk/codon/include/peglib.h
pscdk/codon/include/codon/cir/attribute.h
pscdk/codon/include/codon/cir/base.h
pscdk/codon/include/codon/cir/cir.h
pscdk/codon/include/codon/cir/const.h
pscdk/codon/include/codon/cir/flow.h
pscdk/codon/include/codon/cir/func.h
pscdk/codon/include/codon/cir/instr.h
pscdk/codon/include/codon/cir/module.h
pscdk/codon/include/codon/cir/value.h
pscdk/codon/include/codon/cir/var.h
pscdk/codon/include/codon/cir/analyze/analysis.h
pscdk/codon/include/codon/cir/analyze/dataflow/capture.h
pscdk/codon/include/codon/cir/analyze/dataflow/cfg.h
pscdk/codon/include/codon/cir/analyze/dataflow/dominator.h
pscdk/codon/include/codon/cir/analyze/dataflow/reaching.h
pscdk/codon/include/codon/cir/analyze/module/global_vars.h
pscdk/codon/include/codon/cir/analyze/module/side_effect.h
pscdk/codon/include/codon/cir/dsl/codegen.h
pscdk/codon/include/codon/cir/dsl/nodes.h
pscdk/codon/include/codon/cir/llvm/gpu.h
pscdk/codon/include/codon/cir/llvm/lld.h
pscdk/codon/include/codon/cir/llvm/llvisitor.h
pscdk/codon/include/codon/cir/llvm/llvm.h
pscdk/codon/include/codon/cir/llvm/optimize.h
pscdk/codon/include/codon/cir/transform/manager.h
pscdk/codon/include/codon/cir/transform/pass.h
pscdk/codon/include/codon/cir/transform/rewrite.h
pscdk/codon/include/codon/cir/transform/cleanup/canonical.h
pscdk/codon/include/codon/cir/transform/cleanup/dead_code.h
pscdk/codon/include/codon/cir/transform/cleanup/global_demote.h
pscdk/codon/include/codon/cir/transform/cleanup/replacer.h
pscdk/codon/include/codon/cir/transform/folding/const_fold.h
pscdk/codon/include/codon/cir/transform/folding/const_prop.h
pscdk/codon/include/codon/cir/transform/folding/folding.h
pscdk/codon/include/codon/cir/transform/folding/rule.h
pscdk/codon/include/codon/cir/transform/lowering/imperative.h
pscdk/codon/include/codon/cir/transform/lowering/pipeline.h
pscdk/codon/include/codon/cir/transform/parallel/openmp.h
pscdk-0.1.2.dist-info/METADATA
pscdk-0.1.2.dist-info/WHEEL
pscdk-0.1.2.dist-info/entry_points.txt
pscdk-0.1.2.dist-info/top_level.txt
pscdk-0.1.2.dist-info/RECORD
