Metadata-Version: 2.1
Name: pscdk
Version: 0.1.2
Summary: Python Smart Contract Development Kit
Home-page: https://github.com/uuosio/pscdk
Author: The UUOSIO Team
License: Commercial
Platform: UNKNOWN
